CHANGES.txt
COPYRIGHT.txt
LICENSE.txt
README.txt
bootstrap.py
buildout.cfg
setup.py
src/zamplugin/__init__.py
src/zamplugin.navigation.egg-info/PKG-INFO
src/zamplugin.navigation.egg-info/SOURCES.txt
src/zamplugin.navigation.egg-info/dependency_links.txt
src/zamplugin.navigation.egg-info/namespace_packages.txt
src/zamplugin.navigation.egg-info/not-zip-safe
src/zamplugin.navigation.egg-info/requires.txt
src/zamplugin.navigation.egg-info/top_level.txt
src/zamplugin/navigation/README.txt
src/zamplugin/navigation/__init__.py
src/zamplugin/navigation/browser.py
src/zamplugin/navigation/browser.zcml
src/zamplugin/navigation/configure.zcml
src/zamplugin/navigation/ftesting.zcml
src/zamplugin/navigation/plugin.py
src/zamplugin/navigation/plugin.zcml
src/zamplugin/navigation/tests.py